shravan/__init__.py
shravan/actions.py
shravan/cli.py
shravan/commands.py
shravan/config.py
shravan/config_gui.py
shravan/constants.py
shravan/main.py
shravan/script_manager.py
shravan/token.py
shravan/websocket_client.py
shravan-1.0.0.dist-info/LICENSE
shravan-1.0.0.dist-info/METADATA
shravan-1.0.0.dist-info/WHEEL
shravan-1.0.0.dist-info/entry_points.txt
shravan-1.0.0.dist-info/top_level.txt
shravan-1.0.0.dist-info/RECORD
