Metadata-Version: 2.1
Name: shravan
Version: 1.0.0
Summary: Control your PC using shravan voice commands.
Home-page: https://github.com/exploring-solver/shravan
Author: exploring-solver
License: MIT
Requires-Python: >=3.6
License-File: LICENSE
Requires-Dist: aioconsole==0.8.1
Requires-Dist: attrs==24.2.0
Requires-Dist: certifi==2024.8.30
Requires-Dist: cffi==1.17.1
Requires-Dist: charset-normalizer==3.4.0
Requires-Dist: click==8.1.7
Requires-Dist: colorama==0.4.6
Requires-Dist: comtypes==1.4.8
Requires-Dist: h11==0.14.0
Requires-Dist: idna==3.10
Requires-Dist: outcome==1.3.0.post0
Requires-Dist: packaging==24.1
Requires-Dist: psutil==6.1.0
Requires-Dist: pycaw==20240210
Requires-Dist: pycparser==2.22
Requires-Dist: PyJWT==2.9.0
Requires-Dist: pyperclip==1.9.0
Requires-Dist: PySocks==1.7.1
Requires-Dist: python-dotenv==1.0.1
Requires-Dist: pywin32==308
Requires-Dist: requests==2.32.3
Requires-Dist: schedule==1.2.2
Requires-Dist: selenium==4.26.1
Requires-Dist: sniffio==1.3.1
Requires-Dist: sortedcontainers==2.4.0
Requires-Dist: trio==0.27.0
Requires-Dist: trio-websocket==0.11.1
Requires-Dist: typing-extensions==4.12.2
Requires-Dist: urllib3==2.2.3
Requires-Dist: webdriver-manager==4.0.2
Requires-Dist: websocket-client==1.8.0
Requires-Dist: websockets==13.1
Requires-Dist: wsproto==1.2.0
